LICENSE.txt
MANIFEST.in
README.md
requirements.txt
setup.py
yamlist/__init__.py
yamlist/calculator.py
yamlist/dictexpr.py
yamlist/expr.py
yamlist/listexpr.py
yamlist/main.py
yamlist/strexpr.py
yamlist/userfunc.py
yamlist/yamast.py
yamlist/yamlib.py
yamlist.egg-info/PKG-INFO
yamlist.egg-info/SOURCES.txt
yamlist.egg-info/dependency_links.txt
yamlist.egg-info/entry_points.txt
yamlist.egg-info/requires.txt
yamlist.egg-info/top_level.txt