Metadata-Version: 1.0
Name: yamlist
Version: 0.0.1
Summary: yamlist
Home-page: UNKNOWN
Author: suzuki-navi
Author-email: UNKNOWN
License: UNKNOWN
Platform: UNKNOWN
